<?xml version="1.0" encoding="utf-8" ?><dwsync><file name="decode_bug.php" server="ptedevlinux.doit.wisc.edu//var/www/html/madison/" local="3297962083" remote="3297962083" /><file name="signon.php" server="ptedevlinux.doit.wisc.edu//var/www/html/madison/" local="3297962083" remote="3297962083" /><file name="upgrade_tables_mysql_4_1_2+.sql" server="ptedevlinux.doit.wisc.edu//var/www/html/madison/" local="3297962083" remote="3297962083" /><file name="setup.php" server="ptedevlinux.doit.wisc.edu//var/www/html/madison/" local="3297962083" remote="3297962083" /><file name="check_lang.php" server="ptedevlinux.doit.wisc.edu//var/www/html/madison/" local="3297962083" remote="3297962083" /><file name="create_tables_mysql_4_1_2+.sql" server="ptedevlinux.doit.wisc.edu//var/www/html/madison/" local="3297962083" remote="3297962083" /><file name="upgrade.pl" server="ptedevlinux.doit.wisc.edu//var/www/html/madison/" local="3297962083" remote="3297962083" /><file name="find_unused_messages.sh" server="ptedevlinux.doit.wisc.edu//var/www/html/madison/" local="3297962083" remote="3297962083" /><file name="create-release.sh" server="ptedevlinux.doit.wisc.edu//var/www/html/madison/" local="3297962083" remote="3297962083" /><file name="lang-cleanup.sh" server="ptedevlinux.doit.wisc.edu//var/www/html/madison/" local="3297962083" remote="3297962083" /><file name="remove_control_m.sh" server="ptedevlinux.doit.wisc.edu//var/www/html/madison/" local="3297962083" remote="3297962083" /><file name="convertcfg.pl" server="ptedevlinux.doit.wisc.edu//var/www/html/madison/" local="3297962083" remote="3297962083" /><file name="create_tables.sql" server="ptedevlinux.doit.wisc.edu//var/www/html/madison/" local="3297962083" remote="3297962083" /><file name="check_lang.php" server="atsosxdev.doit.wisc.edu//Groups/web/aris/" local="3297962083" remote="63428540104" /><file name="convertcfg.pl" server="atsosxdev.doit.wisc.edu//Groups/web/aris/" local="3297962083" remote="59133572808" /><file name="create-release.sh" server="atsosxdev.doit.wisc.edu//Groups/web/aris/" local="3297962083" remote="76313441992" /><file name="create_tables.sql" server="atsosxdev.doit.wisc.edu//Groups/web/aris/" local="3297962083" remote="76313441992" /><file name="create_tables_mysql_4_1_2+.sql" server="atsosxdev.doit.wisc.edu//Groups/web/aris/" local="3297962083" remote="132148016841" /><file name="decode_bug.php" server="atsosxdev.doit.wisc.edu//Groups/web/aris/" local="3297962083" remote="63428540105" /><file name="find_unused_messages.sh" server="atsosxdev.doit.wisc.edu//Groups/web/aris/" local="3297962083" remote="102083245769" /><file name="lang-cleanup.sh" server="atsosxdev.doit.wisc.edu//Groups/web/aris/" local="3297962083" remote="67723507401" /><file name="remove_control_m.sh" server="atsosxdev.doit.wisc.edu//Groups/web/aris/" local="3297962083" remote="84903376586" /><file name="setup.php" server="atsosxdev.doit.wisc.edu//Groups/web/aris/" local="3297962083" remote="41953703626" /><file name="signon.php" server="atsosxdev.doit.wisc.edu//Groups/web/aris/" local="3297962083" remote="46248670922" /><file name="upgrade.pl" server="atsosxdev.doit.wisc.edu//Groups/web/aris/" local="3297962083" remote="46248670922" /><file name="upgrade_tables_mysql_4_1_2+.sql" server="atsosxdev.doit.wisc.edu//Groups/web/aris/" local="3297962083" remote="136442984138" /></dwsync>